rattlesume/__init__.py
rattlesume/__main__.py
rattlesume/builder.py
rattlesume/exceptions.py
rattlesume-0.1.2.dist-info/entry_points.txt
rattlesume-0.1.2.dist-info/LICENSE
rattlesume-0.1.2.dist-info/WHEEL
rattlesume-0.1.2.dist-info/METADATA
rattlesume-0.1.2.dist-info/RECORD
