Metadata-Version: 2.1
Name: rattlesume
Version: 0.1.2
Summary: 
License: MIT
Author: Kelton Bassingthwaite
Author-email: keltonbassingthwaite@gmail.com
Requires-Python: >=3.10,<4.0
Classifier: License :: OSI Approved :: MIT License
Classifier: Programming Language :: Python :: 3
Classifier: Programming Language :: Python :: 3.10
Classifier: Programming Language :: Python :: 3.11
Requires-Dist: pyyaml (>=6.0,<7.0)
Requires-Dist: typer[all] (>=0.7.0,<0.8.0)
